srutil/__init__.py
srutil/_datetimeutil.py
srutil/_ioutil.py
srutil/_kutil.py
srutil/_metautil.py
srutil/_networkutil.py
srutil/_numberutil.py
srutil/_pythonutil.py
srutil/_stringutil.py
srutil/_sysutil.py
srutil/util.py
srutil-1.0.3.dist-info/LICENSE
srutil-1.0.3.dist-info/METADATA
srutil-1.0.3.dist-info/WHEEL
srutil-1.0.3.dist-info/top_level.txt
srutil-1.0.3.dist-info/RECORD
