Metadata-Version: 2.1
Name: srutil
Version: 1.0.3
Summary: Common Utils.
Author-email: srg <srg.code@pm.me>
License: Apache License, Version 2.0
Project-URL: Homepage, https://github.com/codesrg/srutil
Project-URL: Bug Tracker, https://github.com/codesrg/srutil/issues
Keywords: srutil,util
Classifier: Programming Language :: Python :: 3
Classifier: License :: OSI Approved :: Apache Software License
Classifier: Operating System :: OS Independent
Requires-Python: >=3.6
License-File: LICENSE
